datasette_x_forwarded_host/__init__.py
datasette_x_forwarded_host-0.1.dist-info/METADATA
datasette_x_forwarded_host-0.1.dist-info/WHEEL
datasette_x_forwarded_host-0.1.dist-info/entry_points.txt
datasette_x_forwarded_host-0.1.dist-info/top_level.txt
datasette_x_forwarded_host-0.1.dist-info/RECORD
