Metadata-Version: 2.1
Name: datasette-x-forwarded-host
Version: 0.1
Summary: Treat the X-Forwarded-Host header as the Host header
Home-page: https://github.com/simonw/datasette-x-forwarded-host
Author: Simon Willison
License: Apache License, Version 2.0
Project-URL: Issues, https://github.com/simonw/datasette-x-forwarded-host/issues
Project-URL: CI, https://github.com/simonw/datasette-x-forwarded-host/actions
Project-URL: Changelog, https://github.com/simonw/datasette-x-forwarded-host/releases
Platform: UNKNOWN
Requires-Python: >=3.6
Requires-Dist: datasette
Provides-Extra: test
Requires-Dist: pytest ; extra == 'test'
Requires-Dist: pytest-asyncio ; extra == 'test'
